parametricGarch/__init__.py
parametricGarch/parametric.py
parametricGarch-0.0.6.dist-info/LICENSE
parametricGarch-0.0.6.dist-info/METADATA
parametricGarch-0.0.6.dist-info/WHEEL
parametricGarch-0.0.6.dist-info/top_level.txt
parametricGarch-0.0.6.dist-info/RECORD
